rgbmon/__init__.py
rgbmon/cli.py
rgbmon/backend/__init__.py
rgbmon/backend/openrgb.py
rgbmon/core/__init__.py
rgbmon/core/backend.py
rgbmon/core/effect.py
rgbmon/core/rgbmon.py
rgbmon/core/source.py
rgbmon/core/task.py
rgbmon/core/utils.py
rgbmon/effect/__init__.py
rgbmon/effect/dot.py
rgbmon/effect/fade.py
rgbmon/effect/fill.py
rgbmon/effect/rainbow.py
rgbmon/source/__init__.py
rgbmon/source/cpu.py
rgbmon/source/memory.py
rgbmon/source/sawtooth.py
rgbmon/source/sine.py
rgbmon/source/temperature.py
rgbmon-0.1.0.dist-info/LICENSE
rgbmon-0.1.0.dist-info/METADATA
rgbmon-0.1.0.dist-info/WHEEL
rgbmon-0.1.0.dist-info/entry_points.txt
rgbmon-0.1.0.dist-info/top_level.txt
rgbmon-0.1.0.dist-info/RECORD
