Metadata-Version: 2.1
Name: rgbmon
Version: 0.1.0
Summary: System monitoring tool that colors your hardware
Home-page: https://github.com/inlart/RGBmon
Author: inlart
Author-email: g@inlart.com
License: UNKNOWN
Platform: UNKNOWN
Classifier: Programming Language :: Python :: 3
Classifier: License :: OSI Approved :: GNU General Public License v3 (GPLv3)
Classifier: Operating System :: OS Independent
Requires-Python: >=3.7
Requires-Dist: openrgb-python
